knopt/__init__.py
knopt-0.3.1.dist-info/LICENSE
knopt-0.3.1.dist-info/METADATA
knopt-0.3.1.dist-info/WHEEL
knopt-0.3.1.dist-info/top_level.txt
knopt-0.3.1.dist-info/RECORD
